mountapi/__init__.py
mountapi/lib.py
mountapi/reloaders.py
mountapi/routing.py
mountapi/runners.py
mountapi/schema.py
mountapi/server.py
mountapi/version.py
mountapi/contrib/__init__.py
mountapi/contrib/output.py
mountapi/core/__init__.py
mountapi/core/app.py
mountapi/core/exceptions.py
mountapi/core/settings.py
mountapi/http/__init__.py
mountapi/http/exceptions.py
mountapi/http/request.py
mountapi/http/response.py
mountapi/http/status.py
mountapi-0.1.0a0.dist-info/METADATA
mountapi-0.1.0a0.dist-info/RECORD
mountapi-0.1.0a0.dist-info/WHEEL
mountapi-0.1.0a0.dist-info/top_level.txt
